{"version": 0.6, "generator": "Overpass API 0.7.62.8 e802775f", "osm3s": {"timestamp_osm_base": "2025-10-04T07:58:35Z", "copyright": "The data included in this document is from www.openstreetmap.org. The data is made available under ODbL."}, "elements": [{"type": "node", "id": 2111379808, "lat": 55.1989384, "lon": -7.4437737}, {"type": "node", "id": 2111379821, "lat": 55.1993341, "lon": -7.443565}, {"type": "node", "id": 2111379824, "lat": 55.1989922, "lon": -7.4435917}, {"type": "node", "id": 2111379877, "lat": 55.1990464, "lon": -7.443304}, {"type": "node", "id": 2111379884, "lat": 55.1992019, "lon": -7.4440126}, {"type": "node", "id": 2111379915, "lat": 55.1989679, "lon": -7.4435697}, {"type": "node", "id": 2121471246, "lat": 55.1981069, "lon": -7.4405603}, {"type": "node", "id": 2121471318, "lat": 55.1984158, "lon": -7.4406806}, {"type": "node", "id": 2121471531, "lat": 55.198206, "lon": -7.4403608}, {"type": "node", "id": 2121471677, "lat": 55.1983343, "lon": -7.4409067}, {"type": "node", "id": 2922107725, "lat": 55.1949599, "lon": -7.0464899}, {"type": "node", "id": 2922107780, "lat": 55.1946242, "lon": -7.047335}, {"type": "node", "id": 2922107799, "lat": 55.1950296, "lon": -7.0477663}, {"type": "node", "id": 2922108220, "lat": 55.1953595, "lon": -7.0469273}, {"type": "node", "id": 3503088565, "lat": 55.1947385, "lon": -7.047452}, {"type": "node", "id": 3503088566, "lat": 55.1948611, "lon": -7.0474117, "tags": {"barrier": "gate"}}, {"type": "node", "id": 3585664997, "lat": 55.2434588, "lon": -7.2767231}, {"type": "node", "id": 3585664998, "lat": 55.2433899, "lon": -7.2758442}, {"type": "node", "id": 3585665016, "lat": 55.2433772, "lon": -7.2759312}, {"type": "node", "id": 3585665023, "lat": 55.2436978, "lon": -7.2758421}, {"type": "node", "id": 3585665042, "lat": 55.2432484, "lon": -7.2761768}, {"type": "node", "id": 3585665086, "lat": 55.2437295, "lon": -7.276412}, {"type": "node", "id": 4244677430, "lat": 55.1949807, "lon": -7.0476633, "tags": {"barrier": "gate"}}, {"type": "node", "id": 4349693822, "lat": 55.1983715, "lon": -7.4409634}, {"type": "node", "id": 4349693823, "lat": 55.1991544, "lon": -7.4439696}, {"type": "node", "id": 4349693824, "lat": 55.1992866, "lon": -7.4435218}, {"type": "node", "id": 4391375654, "lat": 55.2435939, "lon": -7.2765679, "tags": {"barrier": "gate"}}, {"type": "node", "id": 6636709331, "lat": 55.1985755, "lon": -7.4418655}, {"type": "node", "id": 6636709332, "lat": 55.1988026, "lon": -7.4412829}, {"type": "node", "id": 6636709333, "lat": 55.1986339, "lon": -7.441081}, {"type": "node", "id": 6636709334, "lat": 55.1984068, "lon": -7.4416635}, {"type": "node", "id": 6636709335, "lat": 55.1984496, "lon": -7.4415536}, {"type": "node", "id": 6636709338, "lat": 55.198515, "lon": -7.441386}, {"type": "node", "id": 6636709339, "lat": 55.1986718, "lon": -7.4416184}, {"type": "node", "id": 10293712732, "lat": 55.198449, "lon": -7.4408073}, {"type": "node", "id": 10293712733, "lat": 55.1983943, "lon": -7.440724}, {"type": "way", "id": 201188312, "nodes": [2111379884, 2111379821, 4349693824, 2111379877, 2111379915, 2111379824, 2111379808, 4349693823, 2111379884], "tags": {"frequency": "50", "name": "Drumlough Hill (1) 38kV Substation", "operator": "ESB Networks", "operator:wikidata": "Q3050566", "phases": "3", "power": "substation", "substation": "generation", "voltage": "38000"}}, {"type": "way", "id": 202169641, "nodes": [2121471677, 4349693822, 10293712732, 10293712733, 2121471318, 2121471531, 2121471246, 2121471677], "tags": {"frequency": "50", "name": "Drumlough Hill (2) 38kV Substation", "operator": "ESB Networks", "operator:wikidata": "Q3050566", "phases": "3", "power": "substation", "substation": "generation", "voltage": "38000"}}, {"type": "way", "id": 288658349, "nodes": [2922107780, 2922107725, 2922108220, 2922107799, 4244677430, 3503088566, 3503088565, 2922107780], "tags": {"barrier": "fence", "frequency": "50", "name": "Moville 38kV Substation", "operator": "ESB Networks", "operator:wikidata": "Q3050566", "operator:wikipedia": "en:ESB Group", "phases": "3", "power": "substation", "substation": "distribution", "voltage": "38000", "voltage:primary": "38000", "voltage:secondary": "20000"}}, {"type": "way", "id": 352796957, "nodes": [3585665023, 3585665086, 4391375654, 3585664997, 3585665042, 3585665016, 3585664998, 3585665023], "tags": {"barrier": "fence", "fixme": "name", "frequency": "50", "name": "Carndonagh 38kV", "operator": "ESB Networks", "operator:wikidata": "Q3050566", "operator:wikipedia": "en:ESB Group", "phases": "3", "power": "substation", "substation": "distribution", "voltage": "38000", "voltage:primary": "38000", "voltage:secondary": "20000"}}, {"type": "way", "id": 706299522, "nodes": [6636709331, 6636709339, 6636709332, 6636709333, 6636709338, 6636709335, 6636709334, 6636709331], "tags": {"frequency": "50", "name": "Drumlough Hill (3) 38kV Substation", "operator": "ESB Networks", "operator:wikidata": "Q3050566", "phases": "3", "power": "substation", "substation": "generation", "voltage": "38000"}}]}